stkhelper/__init__.py
stkhelper/application.py
stkhelper/areatarget.py
stkhelper/satellite.py
stkhelper/scenario.py
stkhelper/scenarioobject.py
stkhelper/schedtopower.py
stkhelper/sensor.py
stkhelper/toolbox.py
stkhelper-4.0.0.dist-info/METADATA
stkhelper-4.0.0.dist-info/WHEEL
stkhelper-4.0.0.dist-info/top_level.txt
stkhelper-4.0.0.dist-info/RECORD
