Metadata-Version: 2.1
Name: stkhelper
Version: 4.0.0
Summary: Uses the STK software to create simulations for satellite testing
Home-page: https://github.com/cnmcferren/stkhelper
Author: W. Conor McFerren
Author-email: cnmcferren@gmail.com
License: UNKNOWN
Platform: UNKNOWN
Requires-Dist: comtypes
Requires-Dist: pypiwin32
Requires-Dist: datetime
Requires-Dist: wheel
Requires-Dist: pandas
